illumidesk_theia_proxy/__init__.py
illumidesk_theia_proxy/icons/theia.svg
illumidesk_theia_proxy-0.1.5.dist-info/LICENSE
illumidesk_theia_proxy-0.1.5.dist-info/METADATA
illumidesk_theia_proxy-0.1.5.dist-info/WHEEL
illumidesk_theia_proxy-0.1.5.dist-info/entry_points.txt
illumidesk_theia_proxy-0.1.5.dist-info/top_level.txt
illumidesk_theia_proxy-0.1.5.dist-info/RECORD
