Metadata-Version: 2.1
Name: illumidesk-theia-proxy
Version: 0.1.5
Summary: hello@illumidesk.com
Home-page: https://github.com/illumidesk/illumidesk-theia-proxy
Author: IllumiDesk Team
License: UNKNOWN
Keywords: jupyter,theia,jupyterhub
Platform: UNKNOWN
Classifier: Framework :: Jupyter
Requires-Dist: jupyter-server-proxy
